<zapaddon>
	<name>Vulnerable JS libraries detection</name>
	<version>1</version>
	<description>Detects use of insecure versions of JavaScript libraries using database of Retire.js</description>
	<author>Nikita Mundhada</author>
	<url></url>
	<changes></changes>
	<dependson/>
	<extensions>
	    <extension>org.zaproxy.zap.extension.retire.RetireExtension</extension>
	</extensions>
	<ascanrules/>
	<pscanrules>
		<pscanrule>org.zaproxy.zap.extension.retire.RetirePassiveScanner</pscanrule>
	</pscanrules>
	<filters/>
	<files/>
	<not-before-version>2.3.0</not-before-version>
	<not-from-version></not-from-version>
</zapaddon>
